[
  {
    "Neighbourhood": "AVer-o-Mar, Amorim e Terroso",
    "RoomType": "Entire home/apt",
    "NumberOfListings": 4
  },
  {
    "Neighbourhood": "Aguçadoura e Navais",
    "RoomType": "Entire home/apt",
    "NumberOfListings": 1
  },
  {
    "Neighbourhood": "Aldoar, Foz do Douro e Nevogilde",
    "RoomType": "Entire home/apt",
    "NumberOfListings": 16
  },
  {
    "Neighbourhood": "Aldoar, Foz do Douro e Nevogilde",
    "RoomType": "Private room",
    "NumberOfListings": 3
  },
  {
    "Neighbourhood": "Alfena",
    "RoomType": "Entire home/apt",
    "NumberOfListings": 1
  },
  {
    "Neighbourhood": "Alvarelhos e Guidões",
    "RoomType": "Entire home/apt",
    "NumberOfListings": 1
  },
  {
    "Neighbourhood": "Alvarenga",
    "RoomType": "Entire home/apt",
    "NumberOfListings": 1
  },
  {
    "Neighbourhood": "Anta e Guetim",
    "RoomType": "Entire home/apt",
    "NumberOfListings": 1
  },
  {
    "Neighbourhood": "Anta e Guetim",
    "RoomType": "Private room",
    "NumberOfListings": 1
  },
  {
    "Neighbourhood": "Arcozelo",
    "RoomType": "Entire home/apt",
    "NumberOfListings": 5
  },
  {
    "Neighbourhood": "Arouca e Burgo",
    "RoomType": "Entire home/apt",
    "NumberOfListings": 1
  },
  {
    "Neighbourhood": "Balazar",
    "RoomType": "Entire home/apt",
    "NumberOfListings": 1
  },
  {
    "Neighbourhood": "Bonfim",
    "RoomType": "Entire home/apt",
    "NumberOfListings": 53
  },
  {
    "Neighbourhood": "Bonfim",
    "RoomType": "Private room",
    "NumberOfListings": 3
  },
  {
    "Neighbourhood": "Campanhã",
    "RoomType": "Entire home/apt",
    "NumberOfListings": 5
  },
  {
    "Neighbourhood": "Campanhã",
    "RoomType": "Private room",
    "NumberOfListings": 5
  },
  {
    "Neighbourhood": "Campo e Sobrado",
    "RoomType": "Entire home/apt",
    "NumberOfListings": 1
  },
  {
    "Neighbourhood": "Canedo, Vale e Vila Maior",
    "RoomType": "Entire home/apt",
    "NumberOfListings": 2
  },
  {
    "Neighbourhood": "Canelas e Espiunca",
    "RoomType": "Entire home/apt",
    "NumberOfListings": 1
  },
  {
    "Neighbourhood": "Canidelo",
    "RoomType": "Entire home/apt",
    "NumberOfListings": 7
  },
  {
    "Neighbourhood": "Castêlo da Maia",
    "RoomType": "Private room",
    "NumberOfListings": 1
  },
  {
    "Neighbourhood": "Cedofeita, Ildefonso, Sé, Miragaia, Nicolau, Vitória",
    "RoomType": "Entire home/apt",
    "NumberOfListings": 424
  },
  {
    "Neighbourhood": "Cedofeita, Ildefonso, Sé, Miragaia, Nicolau, Vitória",
    "RoomType": "Private room",
    "NumberOfListings": 49
  },
  {
    "Neighbourhood": "Cedofeita, Ildefonso, Sé, Miragaia, Nicolau, Vitória",
    "RoomType": "Shared room",
    "NumberOfListings": 6
  },
  {
    "Neighbourhood": "Cete",
    "RoomType": "Entire home/apt",
    "NumberOfListings": 3
  },
  {
    "Neighbourhood": "Custóias, Leça do Balio e Guifões",
    "RoomType": "Entire home/apt",
    "NumberOfListings": 1
  },
  {
    "Neighbourhood": "Ermesinde",
    "RoomType": "Entire home/apt",
    "NumberOfListings": 1
  },
  {
    "Neighbourhood": "Espinho",
    "RoomType": "Entire home/apt",
    "NumberOfListings": 4
  },
  {
    "Neighbourhood": "Espinho",
    "RoomType": "Private room",
    "NumberOfListings": 3
  },
  {
    "Neighbourhood": "Fornelo e Vairão",
    "RoomType": "Private room",
    "NumberOfListings": 1
  },
  {
    "Neighbourhood": "Foz do Sousa e Covelo",
    "RoomType": "Entire home/apt",
    "NumberOfListings": 1
  },
  {
    "Neighbourhood": "Gulpilhares e Valadares",
    "RoomType": "Entire home/apt",
    "NumberOfListings": 4
  },
  {
    "Neighbourhood": "Junqueira",
    "RoomType": "Entire home/apt",
    "NumberOfListings": 1
  },
  {
    "Neighbourhood": "Lomba",
    "RoomType": "Entire home/apt",
    "NumberOfListings": 1
  },
  {
    "Neighbourhood": "Lordelo do Ouro e Massarelos",
    "RoomType": "Entire home/apt",
    "NumberOfListings": 21
  },
  {
    "Neighbourhood": "Lordelo do Ouro e Massarelos",
    "RoomType": "Private room",
    "NumberOfListings": 4
  },
  {
    "Neighbourhood": "Macieira de Cambra",
    "RoomType": "Entire home/apt",
    "NumberOfListings": 1
  },
  {
    "Neighbourhood": "Madalena",
    "RoomType": "Entire home/apt",
    "NumberOfListings": 4
  },
  {
    "Neighbourhood": "Mafamude e Vilar do Paraíso",
    "RoomType": "Entire home/apt",
    "NumberOfListings": 8
  },
  {
    "Neighbourhood": "Mafamude e Vilar do Paraíso",
    "RoomType": "Private room",
    "NumberOfListings": 2
  },
  {
    "Neighbourhood": "Matosinhos e Leça da Palmeira",
    "RoomType": "Entire home/apt",
    "NumberOfListings": 5
  },
  {
    "Neighbourhood": "Matosinhos e Leça da Palmeira",
    "RoomType": "Private room",
    "NumberOfListings": 1
  },
  {
    "Neighbourhood": "Melres e Medas",
    "RoomType": "Entire home/apt",
    "NumberOfListings": 2
  },
  {
    "Neighbourhood": "Mindelo",
    "RoomType": "Entire home/apt",
    "NumberOfListings": 2
  },
  {
    "Neighbourhood": "O. Azeméis, Riba-Ul, Ul, Macinhata da Seixa, Madail",
    "RoomType": "Entire home/apt",
    "NumberOfListings": 1
  },
  {
    "Neighbourhood": "Oliveira do Douro",
    "RoomType": "Entire home/apt",
    "NumberOfListings": 1
  },
  {
    "Neighbourhood": "Ossela",
    "RoomType": "Entire home/apt",
    "NumberOfListings": 1
  },
  {
    "Neighbourhood": "Parada de Todeia",
    "RoomType": "Entire home/apt",
    "NumberOfListings": 2
  },
  {
    "Neighbourhood": "Paranhos",
    "RoomType": "Entire home/apt",
    "NumberOfListings": 10
  },
  {
    "Neighbourhood": "Paranhos",
    "RoomType": "Private room",
    "NumberOfListings": 13
  },
  {
    "Neighbourhood": "Perafita, Lavra e Santa Cruz do Bispo",
    "RoomType": "Entire home/apt",
    "NumberOfListings": 2
  },
  {
    "Neighbourhood": "Perafita, Lavra e Santa Cruz do Bispo",
    "RoomType": "Private room",
    "NumberOfListings": 5
  },
  {
    "Neighbourhood": "Póvoa de Varzim, Beiriz e Argivai",
    "RoomType": "Entire home/apt",
    "NumberOfListings": 3
  },
  {
    "Neighbourhood": "Ramalde",
    "RoomType": "Entire home/apt",
    "NumberOfListings": 10
  },
  {
    "Neighbourhood": "Ramalde",
    "RoomType": "Private room",
    "NumberOfListings": 3
  },
  {
    "Neighbourhood": "Roge",
    "RoomType": "Entire home/apt",
    "NumberOfListings": 4
  },
  {
    "Neighbourhood": "Rossas",
    "RoomType": "Entire home/apt",
    "NumberOfListings": 1
  },
  {
    "Neighbourhood": "Sandim, Olival, Lever e Crestuma",
    "RoomType": "Entire home/apt",
    "NumberOfListings": 2
  },
  {
    "Neighbourhood": "Santa Eulália",
    "RoomType": "Entire home/apt",
    "NumberOfListings": 1
  },
  {
    "Neighbourhood": "Santa Maria da Feira, Travanca, Sanfins e Espargo",
    "RoomType": "Entire home/apt",
    "NumberOfListings": 1
  },
  {
    "Neighbourhood": "Santa Marinha e São Pedro da Afurada",
    "RoomType": "Entire home/apt",
    "NumberOfListings": 22
  },
  {
    "Neighbourhood": "Santa Marinha e São Pedro da Afurada",
    "RoomType": "Private room",
    "NumberOfListings": 3
  },
  {
    "Neighbourhood": "São Félix da Marinha",
    "RoomType": "Entire home/apt",
    "NumberOfListings": 1
  },
  {
    "Neighbourhood": "São Mamede de Infesta e Senhora da Hora",
    "RoomType": "Entire home/apt",
    "NumberOfListings": 3
  },
  {
    "Neighbourhood": "São Mamede de Infesta e Senhora da Hora",
    "RoomType": "Private room",
    "NumberOfListings": 1
  },
  {
    "Neighbourhood": "São Pedro Fins",
    "RoomType": "Entire home/apt",
    "NumberOfListings": 1
  },
  {
    "Neighbourhood": "São Pedro de Castelões",
    "RoomType": "Entire home/apt",
    "NumberOfListings": 1
  },
  {
    "Neighbourhood": "Tropeço",
    "RoomType": "Entire home/apt",
    "NumberOfListings": 1
  },
  {
    "Neighbourhood": "Vila Chã",
    "RoomType": "Entire home/apt",
    "NumberOfListings": 4
  },
  {
    "Neighbourhood": "Vila de Cucujães",
    "RoomType": "Entire home/apt",
    "NumberOfListings": 1
  },
  {
    "Neighbourhood": "Vila do Conde",
    "RoomType": "Entire home/apt",
    "NumberOfListings": 7
  },
  {
    "Neighbourhood": "Árvore",
    "RoomType": "Entire home/apt",
    "NumberOfListings": 2
  }
]